{
  "$schema": "https://developer.microsoft.com/json-schemas/fabric/item/report/definition/visualContainer/2.5.0/schema.json",
  "name": "6258f6c317fd5840a818",
  "position": {
    "x": 768.51752021563334,
    "y": 478.70619946091642,
    "z": 0,
    "height": 219.94609164420484,
    "width": 477.84366576819406,
    "tabOrder": 1000
  },
  "visual": {
    "visualType": "columnChart",
    "query": {
      "queryState": {
        "Category": {
          "projections": [
            {
              "field": {
                "Column": {
                  "Expression": {
                    "SourceRef": {
                      "Entity": "medalha"
                    }
                  },
                  "Property": "Dias_Após_Abertura"
                }
              },
              "queryRef": "medalha.Dias_Após_Abertura",
              "nativeQueryRef": "Dias após a cerimônia de abertura",
              "active": true,
              "displayName": "Dias após a cerimônia de abertura"
            }
          ]
        },
        "Y": {
          "projections": [
            {
              "field": {
                "Aggregation": {
                  "Expression": {
                    "Column": {
                      "Expression": {
                        "SourceRef": {
                          "Entity": "medalha"
                        }
                      },
                      "Property": "Dias_Após_Abertura"
                    }
                  },
                  "Function": 5
                }
              },
              "queryRef": "CountNonNull(medalha.Dias_Após_Abertura)",
              "nativeQueryRef": "Número de medalhas",
              "displayName": "Número de medalhas"
            }
          ]
        }
      },
      "sortDefinition": {
        "sort": [
          {
            "field": {
              "Column": {
                "Expression": {
                  "SourceRef": {
                    "Entity": "medalha"
                  }
                },
                "Property": "Dias_Após_Abertura"
              }
            },
            "direction": "Ascending"
          }
        ]
      }
    },
    "objects": {
      "valueAxis": [
        {
          "properties": {
            "titleColor": {
              "solid": {
                "color": {
                  "expr": {
                    "Literal": {
                      "Value": "'#2C497F'"
                    }
                  }
                }
              }
            }
          }
        }
      ],
      "categoryAxis": [
        {
          "properties": {
            "end": {
              "expr": {
                "Aggregation": {
                  "Expression": {
                    "Column": {
                      "Expression": {
                        "SourceRef": {
                          "Entity": "medalha"
                        }
                      },
                      "Property": "Dias_Após_Abertura"
                    }
                  },
                  "Function": 4
                }
              }
            },
            "start": {
              "expr": {
                "Literal": {
                  "Value": "0D"
                }
              }
            },
            "innerPadding": {
              "expr": {
                "Literal": {
                  "Value": "50L"
                }
              }
            },
            "titleColor": {
              "solid": {
                "color": {
                  "expr": {
                    "Literal": {
                      "Value": "'#2C497F'"
                    }
                  }
                }
              }
            }
          }
        }
      ],
      "dataPoint": [
        {
          "properties": {
            "fillTransparency": {
              "expr": {
                "Literal": {
                  "Value": "0D"
                }
              }
            },
            "fill": {
              "solid": {
                "color": {
                  "expr": {
                    "Literal": {
                      "Value": "'#2C497F'"
                    }
                  }
                }
              }
            }
          }
        }
      ],
      "ribbonBands": [
        {
          "properties": {
            "show": {
              "expr": {
                "Literal": {
                  "Value": "false"
                }
              }
            }
          }
        }
      ],
      "labels": [
        {
          "properties": {
            "show": {
              "expr": {
                "Literal": {
                  "Value": "false"
                }
              }
            }
          }
        }
      ],
      "zoom": [
        {
          "properties": {
            "show": {
              "expr": {
                "Literal": {
                  "Value": "false"
                }
              }
            }
          }
        }
      ]
    },
    "visualContainerObjects": {
      "background": [
        {
          "properties": {
            "color": {
              "solid": {
                "color": {
                  "expr": {
                    "Literal": {
                      "Value": "'#E9DEAF'"
                    }
                  }
                }
              }
            }
          }
        }
      ],
      "title": [
        {
          "properties": {
            "show": {
              "expr": {
                "Literal": {
                  "Value": "false"
                }
              }
            }
          }
        }
      ]
    },
    "drillFilterOtherVisuals": true
  }
}